oai/__init__.py
oai/__main__.py
oai/cli/__init__.py
oai/cli/commands.py
oai/cli/parser.py
oai/cli/utils.py
oai/core/__init__.py
oai/core/config.py
oai/core/exceptions.py
oai/openai_api.py
cmi_oai_cli-0.0.1a6.dist-info/LICENSE
cmi_oai_cli-0.0.1a6.dist-info/METADATA
cmi_oai_cli-0.0.1a6.dist-info/WHEEL
cmi_oai_cli-0.0.1a6.dist-info/entry_points.txt
cmi_oai_cli-0.0.1a6.dist-info/RECORD
