Metadata-Version: 2.1
Name: cmi-oai-cli
Version: 0.0.1a6
Summary: A CLI for OpenAI's API
License: LGPL-2.1
Author: Reinder Vos de Wael
Author-email: reinder.vosdewael@childmind.org
Requires-Python: >3.8,<4.0
Classifier: License :: OSI Approved
Classifier: Programming Language :: Python :: 3
Classifier: Programming Language :: Python :: 3.9
Classifier: Programming Language :: Python :: 3.10
Classifier: Programming Language :: Python :: 3.11
Classifier: Programming Language :: Python :: 3.12
Provides-Extra: docs
Requires-Dist: ffmpeg-python (>=0.2.0,<0.3.0)
Requires-Dist: openai (>=1.3.7,<2.0.0)
Requires-Dist: pydantic (>=2.5.2,<3.0.0)
Requires-Dist: pydantic-settings (>=2.1.0,<3.0.0)
Requires-Dist: requests (>=2.31.0,<3.0.0)
